pandas_ta_classic/__init__.py
pandas_ta_classic/_meta.py
pandas_ta_classic/_version.py
pandas_ta_classic/core.py
pandas_ta_classic/custom.py
pandas_ta_classic/candles/__init__.py
pandas_ta_classic/candles/cdl_doji.py
pandas_ta_classic/candles/cdl_inside.py
pandas_ta_classic/candles/cdl_pattern.py
pandas_ta_classic/candles/cdl_z.py
pandas_ta_classic/candles/ha.py
pandas_ta_classic/cycles/__init__.py
pandas_ta_classic/cycles/ebsw.py
pandas_ta_classic/momentum/__init__.py
pandas_ta_classic/momentum/ao.py
pandas_ta_classic/momentum/apo.py
pandas_ta_classic/momentum/bias.py
pandas_ta_classic/momentum/bop.py
pandas_ta_classic/momentum/brar.py
pandas_ta_classic/momentum/cci.py
pandas_ta_classic/momentum/cfo.py
pandas_ta_classic/momentum/cg.py
pandas_ta_classic/momentum/cmo.py
pandas_ta_classic/momentum/coppock.py
pandas_ta_classic/momentum/cti.py
pandas_ta_classic/momentum/dm.py
pandas_ta_classic/momentum/er.py
pandas_ta_classic/momentum/eri.py
pandas_ta_classic/momentum/fisher.py
pandas_ta_classic/momentum/inertia.py
pandas_ta_classic/momentum/kdj.py
pandas_ta_classic/momentum/kst.py
pandas_ta_classic/momentum/macd.py
pandas_ta_classic/momentum/mom.py
pandas_ta_classic/momentum/pgo.py
pandas_ta_classic/momentum/ppo.py
pandas_ta_classic/momentum/psl.py
pandas_ta_classic/momentum/pvo.py
pandas_ta_classic/momentum/qqe.py
pandas_ta_classic/momentum/roc.py
pandas_ta_classic/momentum/rsi.py
pandas_ta_classic/momentum/rsx.py
pandas_ta_classic/momentum/rvgi.py
pandas_ta_classic/momentum/slope.py
pandas_ta_classic/momentum/smi.py
pandas_ta_classic/momentum/squeeze.py
pandas_ta_classic/momentum/squeeze_pro.py
pandas_ta_classic/momentum/stc.py
pandas_ta_classic/momentum/stoch.py
pandas_ta_classic/momentum/stochrsi.py
pandas_ta_classic/momentum/td_seq.py
pandas_ta_classic/momentum/trix.py
pandas_ta_classic/momentum/tsi.py
pandas_ta_classic/momentum/uo.py
pandas_ta_classic/momentum/willr.py
pandas_ta_classic/overlap/__init__.py
pandas_ta_classic/overlap/alma.py
pandas_ta_classic-0.3.37.dist-info/licenses/LICENSE
pandas_ta_classic-0.3.37.dist-info/METADATA
pandas_ta_classic-0.3.37.dist-info/WHEEL
pandas_ta_classic-0.3.37.dist-info/top_level.txt
pandas_ta_classic-0.3.37.dist-info/RECORD
