Metadata-Version: 2.4
Name: pandas-ta-classic
Version: 0.3.37
Summary: Technical Analysis Indicators - Pandas TA Classic is an easy to use Python 3 Pandas Extension with 141 indicators, 62 TA-Lib patterns (203 total)
Author: xgboosted
Maintainer: xgboosted
License: MIT
Project-URL: Homepage, https://github.com/xgboosted/pandas-ta-classic
Project-URL: Repository, https://github.com/xgboosted/pandas-ta-classic.git
Project-URL: Documentation, https://xgboosted.github.io/pandas-ta-classic/
Project-URL: Bug Tracker, https://github.com/xgboosted/pandas-ta-classic/issues
Keywords: technical analysis,trading,python3,pandas
Classifier: Development Status :: 5 - Production/Stable
Classifier: Operating System :: OS Independent
Classifier: Natural Language :: English
Classifier: Intended Audience :: Developers
Classifier: Intended Audience :: Financial and Insurance Industry
Classifier: Intended Audience :: Science/Research
Classifier: Topic :: Office/Business :: Financial
Classifier: Topic :: Office/Business :: Financial :: Investment
Classifier: Topic :: Scientific/Engineering
Classifier: Topic :: Scientific/Engineering :: Information Analysis
Classifier: Programming Language :: Python :: 3.9
Classifier: Programming Language :: Python :: 3.10
Classifier: Programming Language :: Python :: 3.11
Classifier: Programming Language :: Python :: 3.12
Classifier: Programming Language :: Python :: 3.13
Requires-Python: >=3.9
License-File: LICENSE
Requires-Dist: numpy>=2.0.0
Requires-Dist: pandas>=2.0.0
Requires-Dist: python-dateutil>=2.8.1
Requires-Dist: pytz>=2021.1
Requires-Dist: six>=1.16.0
Provides-Extra: optional
Requires-Dist: scipy; extra == "optional"
Requires-Dist: sklearn; extra == "optional"
Requires-Dist: statsmodels; extra == "optional"
Requires-Dist: stochastic; extra == "optional"
Requires-Dist: talib; extra == "optional"
Requires-Dist: tqdm; extra == "optional"
Provides-Extra: dev
Requires-Dist: pandas-ta-classic[test]; extra == "dev"
Requires-Dist: pandas-ta-classic[docs]; extra == "dev"
Requires-Dist: mypy>=1.0.0; extra == "dev"
Requires-Dist: black>=23.0.0; extra == "dev"
Requires-Dist: flake8>=6.0.0; extra == "dev"
Requires-Dist: isort>=5.0.0; extra == "dev"
Requires-Dist: build>=0.10.0; extra == "dev"
Requires-Dist: twine>=4.0.0; extra == "dev"
Requires-Dist: pre-commit>=3.0.0; extra == "dev"
Provides-Extra: test
Requires-Dist: pytest>=7.0.0; extra == "test"
Requires-Dist: pytest-cov>=4.0.0; extra == "test"
Requires-Dist: pytest-benchmark>=4.0.0; extra == "test"
Requires-Dist: hypothesis>=6.0.0; extra == "test"
Provides-Extra: docs
Requires-Dist: sphinx>=5.0.0; extra == "docs"
Requires-Dist: sphinx-rtd-theme>=1.0.0; extra == "docs"
Requires-Dist: myst-parser>=2.0.0; extra == "docs"
Requires-Dist: matplotlib; extra == "docs"
Requires-Dist: mplfinance; extra == "docs"
Provides-Extra: performance
Requires-Dist: numba>=0.58.0; extra == "performance"
Requires-Dist: cython>=3.0.0; extra == "performance"
Provides-Extra: integration
Requires-Dist: vectorbt; extra == "integration"
Requires-Dist: backtrader; extra == "integration"
Requires-Dist: yfinance; extra == "integration"
Requires-Dist: alphaVantage-api; extra == "integration"
Provides-Extra: all
Requires-Dist: pandas-ta-classic[dev,docs,integration,optional,performance,test]; extra == "all"
Dynamic: license-file
